[
  {"slug":"react","nameVi":"React","nameEn":"React","category":"IT","aliases":["ReactJS","React.js","React 18","React 19"]},
  {"slug":"nextjs","nameVi":"Next.js","nameEn":"Next.js","category":"IT","aliases":["NextJS","Next JS","Next.js 14","Next.js 15"]},
  {"slug":"vuejs","nameVi":"Vue.js","nameEn":"Vue.js","category":"IT","aliases":["VueJS","Vue 3","Vue.js 3","Vue"]},
  {"slug":"angular","nameVi":"Angular","nameEn":"Angular","category":"IT","aliases":["AngularJS","Angular 17","Angular 2+"]},
  {"slug":"nodejs","nameVi":"Node.js","nameEn":"Node.js","category":"IT","aliases":["NodeJS","Node JS","Node"]},
  {"slug":"typescript","nameVi":"TypeScript","nameEn":"TypeScript","category":"IT","aliases":["TS","Typescript"]},
  {"slug":"javascript","nameVi":"JavaScript","nameEn":"JavaScript","category":"IT","aliases":["JS","Javascript","ES6","ES2020"]},
  {"slug":"python","nameVi":"Python","nameEn":"Python","category":"IT","aliases":["Python 3","Python3","py"]},
  {"slug":"java","nameVi":"Java","nameEn":"Java","category":"IT","aliases":["Java 17","Java 11","Java 8","Core Java"]},
  {"slug":"spring-boot","nameVi":"Spring Boot","nameEn":"Spring Boot","category":"IT","aliases":["SpringBoot","Spring Framework","Spring MVC"]},
  {"slug":"csharp","nameVi":"C#","nameEn":"C#","category":"IT","aliases":["C Sharp","CSharp",".NET C#"]},
  {"slug":"dotnet","nameVi":".NET","nameEn":".NET","category":"IT","aliases":[".NET Core","ASP.NET","ASP.NET Core","dotnet"]},
  {"slug":"php","nameVi":"PHP","nameEn":"PHP","category":"IT","aliases":["PHP 8","PHP Laravel"]},
  {"slug":"laravel","nameVi":"Laravel","nameEn":"Laravel","category":"IT","aliases":["Laravel 10","Laravel 11","Laravel PHP"]},
  {"slug":"react-native","nameVi":"React Native","nameEn":"React Native","category":"IT","aliases":["ReactNative","RN","React-Native"]},
  {"slug":"flutter","nameVi":"Flutter","nameEn":"Flutter","category":"IT","aliases":["Flutter Dart","Flutter SDK"]},
  {"slug":"android","nameVi":"Android","nameEn":"Android","category":"IT","aliases":["Android Development","Android Studio","Kotlin Android"]},
  {"slug":"ios","nameVi":"iOS","nameEn":"iOS","category":"IT","aliases":["iOS Development","Swift iOS","Xcode"]},
  {"slug":"sql","nameVi":"SQL","nameEn":"SQL","category":"IT","aliases":["MySQL","T-SQL","SQL Server"]},
  {"slug":"postgresql","nameVi":"PostgreSQL","nameEn":"PostgreSQL","category":"IT","aliases":["Postgres","PgSQL"]},
  {"slug":"mongodb","nameVi":"MongoDB","nameEn":"MongoDB","category":"IT","aliases":["Mongo","MongoDB Atlas","NoSQL MongoDB"]},
  {"slug":"redis","nameVi":"Redis","nameEn":"Redis","category":"IT","aliases":["Redis Cache","Redis Queue"]},
  {"slug":"docker","nameVi":"Docker","nameEn":"Docker","category":"IT","aliases":["Docker Container","Docker Compose","Dockerfile"]},
  {"slug":"kubernetes","nameVi":"Kubernetes","nameEn":"Kubernetes","category":"IT","aliases":["K8s","Kubernetes Orchestration","K8s Cluster"]},
  {"slug":"aws","nameVi":"AWS","nameEn":"Amazon Web Services","category":"IT","aliases":["Amazon Web Services","AWS Cloud","EC2","S3"]},
  {"slug":"gcp","nameVi":"Google Cloud","nameEn":"Google Cloud Platform","category":"IT","aliases":["GCP","Google Cloud Platform","Google Cloud"]},
  {"slug":"azure","nameVi":"Microsoft Azure","nameEn":"Microsoft Azure","category":"IT","aliases":["Azure Cloud","MS Azure","Azure DevOps"]},
  {"slug":"machine-learning","nameVi":"Machine Learning","nameEn":"Machine Learning","category":"IT","aliases":["ML","Máy học","Machine Learning AI"]},
  {"slug":"deep-learning","nameVi":"Deep Learning","nameEn":"Deep Learning","category":"IT","aliases":["DL","Neural Networks","Deep Neural Network"]},
  {"slug":"devops","nameVi":"DevOps","nameEn":"DevOps","category":"IT","aliases":["Dev Ops","CI/CD","DevOps Engineer"]},
  {"slug":"git","nameVi":"Git","nameEn":"Git","category":"IT","aliases":["Git/GitHub","GitHub","GitLab","Version Control"]},
  {"slug":"restful-api","nameVi":"RESTful API","nameEn":"RESTful API","category":"IT","aliases":["REST API","API Design","REST"]},
  {"slug":"graphql","nameVi":"GraphQL","nameEn":"GraphQL","category":"IT","aliases":["Graph QL","GraphQL API"]},
  {"slug":"testing-qa","nameVi":"Kiểm thử phần mềm","nameEn":"Software Testing / QA","category":"IT","aliases":["QA","Software Testing","Manual Testing","Test QA"]},
  {"slug":"selenium","nameVi":"Selenium","nameEn":"Selenium","category":"IT","aliases":["Selenium WebDriver","Selenium Testing","Selenium Java"]},
  {"slug":"cybersecurity","nameVi":"An ninh mạng","nameEn":"Cybersecurity","category":"IT","aliases":["Information Security","Bảo mật thông tin","Cyber Security","InfoSec"]},
  {"slug":"linux","nameVi":"Linux","nameEn":"Linux","category":"IT","aliases":["Linux Server","Ubuntu","CentOS","Bash Linux"]},
  {"slug":"microservices","nameVi":"Microservices","nameEn":"Microservices","category":"IT","aliases":["Micro Services","Microservice Architecture","MSA"]},
  {"slug":"data-analysis","nameVi":"Phân tích dữ liệu","nameEn":"Data Analysis","category":"IT","aliases":["Data Analytics","Phân tích data","DA"]},
  {"slug":"power-bi","nameVi":"Power BI","nameEn":"Power BI","category":"IT","aliases":["PowerBI","Microsoft Power BI","Power BI Desktop"]},
  {"slug":"tableau","nameVi":"Tableau","nameEn":"Tableau","category":"IT","aliases":["Tableau Desktop","Tableau Public","Tableau Visualization"]},

  {"slug":"co-khi","nameVi":"Cơ khí","nameEn":"Mechanical Engineering","category":"KY_THUAT","aliases":["Mechanical Engineering","Kỹ thuật cơ khí","Cơ khí chế tạo"]},
  {"slug":"autocad","nameVi":"AutoCAD","nameEn":"AutoCAD","category":"KY_THUAT","aliases":["Auto CAD","AutoCAD 2D","AutoCAD 3D","CAD"]},
  {"slug":"solidworks","nameVi":"SolidWorks","nameEn":"SolidWorks","category":"KY_THUAT","aliases":["Solid Works","SolidWorks 3D","SW"]},
  {"slug":"dien-cong-nghiep","nameVi":"Điện công nghiệp","nameEn":"Industrial Electrical","category":"KY_THUAT","aliases":["Industrial Electrical","Kỹ thuật điện","Điện CN"]},
  {"slug":"dien-tu","nameVi":"Điện tử","nameEn":"Electronics","category":"KY_THUAT","aliases":["Electronics","Kỹ thuật điện tử","Electronic Engineering"]},
  {"slug":"plc-scada","nameVi":"PLC / SCADA","nameEn":"PLC / SCADA","category":"KY_THUAT","aliases":["PLC","SCADA","Siemens PLC","PLC Programming"]},
  {"slug":"xay-dung","nameVi":"Xây dựng","nameEn":"Civil Engineering","category":"KY_THUAT","aliases":["Civil Engineering","Kỹ thuật xây dựng","Construction"]},
  {"slug":"quan-ly-du-an-xay-dung","nameVi":"Quản lý dự án xây dựng","nameEn":"Construction Project Management","category":"KY_THUAT","aliases":["Construction Project Management","QLDA xây dựng"]},
  {"slug":"revit","nameVi":"Autodesk Revit","nameEn":"Autodesk Revit","category":"KY_THUAT","aliases":["Revit","Revit BIM","BIM Revit"]},
  {"slug":"bim","nameVi":"BIM","nameEn":"Building Information Modeling","category":"KY_THUAT","aliases":["Building Information Modeling","BIM Coordinator"]},
  {"slug":"dieu-hoa-lanh","nameVi":"Điều hòa không khí & Lạnh","nameEn":"HVAC","category":"KY_THUAT","aliases":["HVAC","Air Conditioning","Kỹ thuật lạnh","HVAC Engineer"]},
  {"slug":"an-toan-lao-dong","nameVi":"An toàn lao động","nameEn":"Occupational Health & Safety","category":"KY_THUAT","aliases":["HSE","Occupational Safety","ATVSLĐ","Safety Officer"]},
  {"slug":"kiem-soat-chat-luong","nameVi":"Kiểm soát chất lượng","nameEn":"Quality Control","category":"KY_THUAT","aliases":["QC","Quality Control","QA QC","Kiểm tra chất lượng"]},
  {"slug":"iso-9001","nameVi":"ISO 9001","nameEn":"ISO 9001","category":"KY_THUAT","aliases":["ISO 9001:2015","Hệ thống quản lý chất lượng ISO","QMS"]},
  {"slug":"ky-thuat-moi-truong","nameVi":"Kỹ thuật môi trường","nameEn":"Environmental Engineering","category":"KY_THUAT","aliases":["Environmental Engineering","Môi trường","EHS"]},
  {"slug":"quan-ly-san-xuat","nameVi":"Quản lý sản xuất","nameEn":"Production Management","category":"KY_THUAT","aliases":["Production Management","Manufacturing Management","Quản lý nhà máy"]},
  {"slug":"lean-manufacturing","nameVi":"Lean Manufacturing","nameEn":"Lean Manufacturing","category":"KY_THUAT","aliases":["Lean","Lean 5S","Kaizen","Lean Six Sigma"]},
  {"slug":"dien-lanh","nameVi":"Điện lạnh","nameEn":"Refrigeration Engineering","category":"KY_THUAT","aliases":["Refrigeration","Kỹ thuật điện lạnh","Lạnh thương mại"]},
  {"slug":"vien-thong","nameVi":"Viễn thông","nameEn":"Telecommunications","category":"KY_THUAT","aliases":["Telecommunications","Kỹ thuật viễn thông","Telecom"]},

  {"slug":"ke-toan-tong-hop","nameVi":"Kế toán tổng hợp","nameEn":"General Accounting","category":"KINH_TE","aliases":["General Accounting","Kế toán","Accountant","Kế toán viên"]},
  {"slug":"ke-toan-thue","nameVi":"Kế toán thuế","nameEn":"Tax Accounting","category":"KINH_TE","aliases":["Tax Accounting","Thuế","Kê khai thuế","Tax Accountant"]},
  {"slug":"kiem-toan","nameVi":"Kiểm toán","nameEn":"Auditing","category":"KINH_TE","aliases":["Auditing","Internal Audit","Kiểm toán nội bộ","Audit"]},
  {"slug":"tai-chinh-doanh-nghiep","nameVi":"Tài chính doanh nghiệp","nameEn":"Corporate Finance","category":"KINH_TE","aliases":["Corporate Finance","Financial Planning","FP&A","Tài chính"]},
  {"slug":"phan-tich-tai-chinh","nameVi":"Phân tích tài chính","nameEn":"Financial Analysis","category":"KINH_TE","aliases":["Financial Analysis","FA","Financial Analyst"]},
  {"slug":"ngan-hang","nameVi":"Ngân hàng","nameEn":"Banking","category":"KINH_TE","aliases":["Banking","Ngân hàng thương mại","Commercial Banking"]},
  {"slug":"chung-khoan","nameVi":"Chứng khoán","nameEn":"Securities","category":"KINH_TE","aliases":["Securities","Stock Market","Thị trường chứng khoán","Môi giới CK"]},
  {"slug":"quan-tri-nhan-su","nameVi":"Quản trị nhân sự","nameEn":"Human Resources Management","category":"KINH_TE","aliases":["HR Management","HRM","Nhân sự","Human Resources"]},
  {"slug":"tuyen-dung","nameVi":"Tuyển dụng","nameEn":"Recruitment","category":"KINH_TE","aliases":["Recruitment","Headhunting","Talent Acquisition","Recruiter"]},
  {"slug":"logistics","nameVi":"Logistics","nameEn":"Logistics","category":"KINH_TE","aliases":["Logistics & Supply Chain","Vận tải","Supply Chain"]},
  {"slug":"xuat-nhap-khau","nameVi":"Xuất nhập khẩu","nameEn":"Import / Export","category":"KINH_TE","aliases":["Import Export","XNK","Xuất khẩu","Nhập khẩu","Customs"]},
  {"slug":"quan-ly-kho","nameVi":"Quản lý kho","nameEn":"Warehouse Management","category":"KINH_TE","aliases":["Warehouse Management","Thủ kho","WMS","Kho vận"]},
  {"slug":"erp-sap","nameVi":"SAP ERP","nameEn":"SAP ERP","category":"KINH_TE","aliases":["SAP","SAP S/4HANA","SAP FICO"]},
  {"slug":"excel-nang-cao","nameVi":"Excel nâng cao","nameEn":"Advanced Excel","category":"KINH_TE","aliases":["Advanced Excel","Microsoft Excel","Excel VBA","Pivot Table"]},
  {"slug":"misa","nameVi":"MISA","nameEn":"MISA Accounting","category":"KINH_TE","aliases":["MISA Accounting","Phần mềm MISA","MISA SME","MISA AMIS"]},
  {"slug":"quan-ly-du-an","nameVi":"Quản lý dự án","nameEn":"Project Management","category":"KINH_TE","aliases":["Project Management","PM","PMP","Quản lý DA"]},
  {"slug":"kinh-doanh-quoc-te","nameVi":"Kinh doanh quốc tế","nameEn":"International Business","category":"KINH_TE","aliases":["International Business","Business Development","Kinh doanh QT"]},

  {"slug":"digital-marketing","nameVi":"Digital Marketing","nameEn":"Digital Marketing","category":"MARKETING","aliases":["Marketing số","Online Marketing","Digital MKT"]},
  {"slug":"seo","nameVi":"SEO","nameEn":"SEO","category":"MARKETING","aliases":["Search Engine Optimization","SEO Onpage","SEO Offpage","Technical SEO"]},
  {"slug":"sem-google-ads","nameVi":"Google Ads / SEM","nameEn":"Google Ads / SEM","category":"MARKETING","aliases":["Google Ads","SEM","PPC","Google AdWords","Paid Ads"]},
  {"slug":"social-media-marketing","nameVi":"Social Media Marketing","nameEn":"Social Media Marketing","category":"MARKETING","aliases":["SMM","Facebook Marketing","Tik Tok Marketing","Social Media"]},
  {"slug":"content-marketing","nameVi":"Content Marketing","nameEn":"Content Marketing","category":"MARKETING","aliases":["Content MKT","Content Writing","Viết content","Copywriting"]},
  {"slug":"email-marketing","nameVi":"Email Marketing","nameEn":"Email Marketing","category":"MARKETING","aliases":["Email MKT","Email Campaign","Newsletter Marketing"]},
  {"slug":"ban-hang","nameVi":"Bán hàng","nameEn":"Sales","category":"MARKETING","aliases":["Sales","Kỹ năng bán hàng","B2C Sales","B2B Sales"]},
  {"slug":"cham-soc-khach-hang","nameVi":"Chăm sóc khách hàng","nameEn":"Customer Service","category":"MARKETING","aliases":["Customer Service","CSKH","Customer Support"]},
  {"slug":"pr-truyen-thong","nameVi":"PR & Truyền thông","nameEn":"Public Relations","category":"MARKETING","aliases":["PR","Public Relations","Quan hệ báo chí","Communications"]},
  {"slug":"market-research","nameVi":"Nghiên cứu thị trường","nameEn":"Market Research","category":"MARKETING","aliases":["Market Research","Consumer Insights"]},
  {"slug":"thuong-mai-dien-tu","nameVi":"Thương mại điện tử","nameEn":"E-Commerce","category":"MARKETING","aliases":["E-Commerce","Ecommerce","Shopee","Lazada","TikTok Shop"]},
  {"slug":"brand-management","nameVi":"Quản lý thương hiệu","nameEn":"Brand Management","category":"MARKETING","aliases":["Brand Management","Branding","Brand Strategy","Thương hiệu"]},
  {"slug":"event-marketing","nameVi":"Tổ chức sự kiện & Marketing","nameEn":"Event Marketing","category":"MARKETING","aliases":["Event Marketing","Event Management","Tổ chức sự kiện"]},
  {"slug":"affiliate-marketing","nameVi":"Affiliate Marketing","nameEn":"Affiliate Marketing","category":"MARKETING","aliases":["Affiliate MKT","Tiếp thị liên kết","CPA Marketing"]},
  {"slug":"google-analytics","nameVi":"Google Analytics","nameEn":"Google Analytics","category":"MARKETING","aliases":["GA4","Google Analytics 4","Web Analytics"]},
  {"slug":"facebook-ads","nameVi":"Facebook Ads","nameEn":"Facebook Ads","category":"MARKETING","aliases":["Meta Ads","Facebook Advertising","FB Ads","Instagram Ads"]},
  {"slug":"crm","nameVi":"CRM","nameEn":"Customer Relationship Management","category":"MARKETING","aliases":["Customer Relationship Management","Salesforce CRM","HubSpot CRM"]},

  {"slug":"dieu-duong","nameVi":"Điều dưỡng","nameEn":"Nursing","category":"Y_TE","aliases":["Nursing","Điều dưỡng viên","Nurse"]},
  {"slug":"duoc-hoc","nameVi":"Dược học","nameEn":"Pharmacy","category":"Y_TE","aliases":["Pharmacy","Dược sĩ","Pharmacist","Pharmaceuticals"]},
  {"slug":"y-da-khoa","nameVi":"Y đa khoa","nameEn":"General Medicine","category":"Y_TE","aliases":["General Medicine","Bác sĩ đa khoa","Medical Doctor","MD"]},
  {"slug":"nha-khoa","nameVi":"Nha khoa","nameEn":"Dentistry","category":"Y_TE","aliases":["Dentistry","Nha sĩ","Dental","Dentist"]},
  {"slug":"y-te-cong-cong","nameVi":"Y tế công cộng","nameEn":"Public Health","category":"Y_TE","aliases":["Public Health","Sức khỏe cộng đồng","Epidemiology"]},
  {"slug":"xet-nghiem","nameVi":"Xét nghiệm y tế","nameEn":"Medical Laboratory","category":"Y_TE","aliases":["Medical Laboratory","Lab Testing","Kỹ thuật xét nghiệm"]},
  {"slug":"chan-doan-hinh-anh","nameVi":"Chẩn đoán hình ảnh","nameEn":"Medical Imaging","category":"Y_TE","aliases":["Medical Imaging","Radiology","Siêu âm","X-quang"]},
  {"slug":"vat-ly-tri-lieu","nameVi":"Vật lý trị liệu","nameEn":"Physical Therapy","category":"Y_TE","aliases":["Physical Therapy","Physiotherapy","VLTL","Phục hồi chức năng"]},
  {"slug":"dinh-duong","nameVi":"Dinh dưỡng","nameEn":"Nutrition","category":"Y_TE","aliases":["Nutrition","Dinh dưỡng lâm sàng","Clinical Nutrition","Nutritionist"]},
  {"slug":"ho-sinh","nameVi":"Hộ sinh","nameEn":"Midwifery","category":"Y_TE","aliases":["Midwifery","Hộ sinh viên","Midwife"]},
  {"slug":"tam-ly-hoc","nameVi":"Tâm lý học","nameEn":"Psychology","category":"Y_TE","aliases":["Psychology","Tham vấn tâm lý","Clinical Psychology","Counseling"]},
  {"slug":"y-hoc-co-truyen","nameVi":"Y học cổ truyền","nameEn":"Traditional Medicine","category":"Y_TE","aliases":["Traditional Medicine","Đông y","Y học cổ truyền VN"]},

  {"slug":"giang-day","nameVi":"Giảng dạy","nameEn":"Teaching","category":"SU_PHAM","aliases":["Teaching","Giáo viên","Instructor","Educator"]},
  {"slug":"thiet-ke-bai-giang","nameVi":"Thiết kế bài giảng","nameEn":"Curriculum Design","category":"SU_PHAM","aliases":["Curriculum Design","Lesson Planning","Soạn giáo án","Instructional Design"]},
  {"slug":"dao-tao-phat-trien","nameVi":"Đào tạo & Phát triển","nameEn":"Training & Development","category":"SU_PHAM","aliases":["Training & Development","L&D","Corporate Training","Đào tạo nội bộ"]},
  {"slug":"giao-duc-mam-non","nameVi":"Giáo dục mầm non","nameEn":"Early Childhood Education","category":"SU_PHAM","aliases":["Early Childhood Education","Mầm non","Preschool"]},
  {"slug":"gia-su","nameVi":"Gia sư","nameEn":"Tutoring","category":"SU_PHAM","aliases":["Tutoring","Private Tutor","Dạy kèm"]},
  {"slug":"e-learning","nameVi":"E-Learning","nameEn":"E-Learning","category":"SU_PHAM","aliases":["Online Teaching","Dạy học trực tuyến","LMS","EdTech"]},
  {"slug":"tu-van-huong-nghiep","nameVi":"Tư vấn hướng nghiệp","nameEn":"Career Counseling","category":"SU_PHAM","aliases":["Career Counseling","Hướng nghiệp","Academic Counseling"]},
  {"slug":"ky-nang-thuyet-trinh-dao-tao","nameVi":"Kỹ năng thuyết trình & đào tạo","nameEn":"Presentation & Training Skills","category":"SU_PHAM","aliases":["Training Presentation","Train the Trainer","TTT"]},
  {"slug":"quan-ly-lop-hoc","nameVi":"Quản lý lớp học","nameEn":"Classroom Management","category":"SU_PHAM","aliases":["Classroom Management","Quản lý học sinh","Classroom Control"]},
  {"slug":"giao-duc-dac-biet","nameVi":"Giáo dục đặc biệt","nameEn":"Special Education","category":"SU_PHAM","aliases":["Special Education","Giáo dục trẻ đặc biệt","Inclusive Education"]},
  {"slug":"steam-education","nameVi":"Giáo dục STEM/STEAM","nameEn":"STEM/STEAM Education","category":"SU_PHAM","aliases":["STEM Education","STEAM","Robotics Education","STEM"]},
  {"slug":"kiem-tra-danh-gia","nameVi":"Kiểm tra & Đánh giá học tập","nameEn":"Assessment & Evaluation","category":"SU_PHAM","aliases":["Assessment","Evaluation","Đánh giá giáo dục","Testing Education"]},

  {"slug":"thiet-ke-do-hoa","nameVi":"Thiết kế đồ hoạ","nameEn":"Graphic Design","category":"THIET_KE","aliases":["Graphic Design","Đồ họa","Visual Design","Thiết kế hình ảnh"]},
  {"slug":"adobe-photoshop","nameVi":"Adobe Photoshop","nameEn":"Adobe Photoshop","category":"THIET_KE","aliases":["Photoshop","PS","Adobe PS"]},
  {"slug":"adobe-illustrator","nameVi":"Adobe Illustrator","nameEn":"Adobe Illustrator","category":"THIET_KE","aliases":["Illustrator","AI Illustrator","Adobe AI","Vector Design"]},
  {"slug":"ux-ui-design","nameVi":"Thiết kế UX/UI","nameEn":"UX/UI Design","category":"THIET_KE","aliases":["UX/UI","UI Design","UX Design","User Interface Design"]},
  {"slug":"figma","nameVi":"Figma","nameEn":"Figma","category":"THIET_KE","aliases":["Figma Design","Figma Prototype","Figma UI"]},
  {"slug":"motion-graphics","nameVi":"Motion Graphics","nameEn":"Motion Graphics","category":"THIET_KE","aliases":["After Effects","Motion Design","Adobe After Effects","Animation"]},
  {"slug":"thiet-ke-noi-that","nameVi":"Thiết kế nội thất","nameEn":"Interior Design","category":"THIET_KE","aliases":["Interior Design","Nội thất","3D Interior","Thiết kế thi công"]},
  {"slug":"thiet-ke-kien-truc","nameVi":"Thiết kế kiến trúc","nameEn":"Architectural Design","category":"THIET_KE","aliases":["Architectural Design","Kiến trúc","Architecture"]},
  {"slug":"thiet-ke-thoi-trang","nameVi":"Thiết kế thời trang","nameEn":"Fashion Design","category":"THIET_KE","aliases":["Fashion Design","Thời trang","Thiết kế may mặc"]},
  {"slug":"video-editing","nameVi":"Dựng phim & Chỉnh sửa video","nameEn":"Video Editing","category":"THIET_KE","aliases":["Video Editing","Premiere Pro","Adobe Premiere","Dựng video"]},
  {"slug":"3d-design","nameVi":"Thiết kế 3D","nameEn":"3D Design","category":"THIET_KE","aliases":["3D Modeling","3ds Max","Blender","Cinema 4D","3D Visualization"]},
  {"slug":"branding-design","nameVi":"Thiết kế thương hiệu","nameEn":"Brand Identity Design","category":"THIET_KE","aliases":["Brand Identity","Logo Design","Visual Identity","Brand Design"]},

  {"slug":"tieng-anh","nameVi":"Tiếng Anh","nameEn":"English","category":"NGON_NGU","aliases":["English","tiếng anh","Tiếng Anh giao tiếp","IELTS","TOEIC"]},
  {"slug":"tieng-trung","nameVi":"Tiếng Trung","nameEn":"Chinese","category":"NGON_NGU","aliases":["Chinese","Tiếng Trung Quốc","HSK","Mandarin"]},
  {"slug":"tieng-nhat","nameVi":"Tiếng Nhật","nameEn":"Japanese","category":"NGON_NGU","aliases":["Japanese","JLPT","N2","N3","Tiếng Nhật JLPT"]},
  {"slug":"tieng-han","nameVi":"Tiếng Hàn","nameEn":"Korean","category":"NGON_NGU","aliases":["Korean","TOPIK","Tiếng Hàn TOPIK","OPIc"]},
  {"slug":"tieng-phap","nameVi":"Tiếng Pháp","nameEn":"French","category":"NGON_NGU","aliases":["French","DELF","TCF","Tiếng Pháp DELF"]},
  {"slug":"tieng-duc","nameVi":"Tiếng Đức","nameEn":"German","category":"NGON_NGU","aliases":["German","Deutsch","TestDaF","Goethe","Tiếng Đức"]},
  {"slug":"tieng-tay-ban-nha","nameVi":"Tiếng Tây Ban Nha","nameEn":"Spanish","category":"NGON_NGU","aliases":["Spanish","Español","DELE","Tiếng Tây Ban Nha"]},
  {"slug":"tieng-y","nameVi":"Tiếng Ý","nameEn":"Italian","category":"NGON_NGU","aliases":["Italian","Italiano","Tiếng Ý","CILS"]},
  {"slug":"tieng-nga","nameVi":"Tiếng Nga","nameEn":"Russian","category":"NGON_NGU","aliases":["Russian","Tiếng Nga","TORFL"]},
  {"slug":"tieng-thai","nameVi":"Tiếng Thái","nameEn":"Thai","category":"NGON_NGU","aliases":["Thai","Tiếng Thái Lan"]},
  {"slug":"bien-dich","nameVi":"Biên dịch / Phiên dịch","nameEn":"Translation / Interpretation","category":"NGON_NGU","aliases":["Translation","Interpretation","Dịch thuật","Biên phiên dịch"]},
  {"slug":"tieng-anh-thuong-mai","nameVi":"Tiếng Anh thương mại","nameEn":"Business English","category":"NGON_NGU","aliases":["Business English","English for Business","TOEIC Business","Anh thương mại"]},

  {"slug":"giao-tiep-hieu-qua","nameVi":"Giao tiếp hiệu quả","nameEn":"Effective Communication","category":"KY_NANG_MEM","aliases":["Communication Skills","Kỹ năng giao tiếp","Interpersonal Skills"]},
  {"slug":"lanh-dao","nameVi":"Lãnh đạo","nameEn":"Leadership","category":"KY_NANG_MEM","aliases":["Leadership","Kỹ năng lãnh đạo","Team Leadership","Management Skills"]},
  {"slug":"lam-viec-nhom","nameVi":"Làm việc nhóm","nameEn":"Teamwork","category":"KY_NANG_MEM","aliases":["Teamwork","Collaboration","Kỹ năng nhóm","Team Player"]},
  {"slug":"giai-quyet-van-de","nameVi":"Giải quyết vấn đề","nameEn":"Problem Solving","category":"KY_NANG_MEM","aliases":["Problem Solving","Kỹ năng giải quyết vấn đề","Critical Thinking"]},
  {"slug":"quan-ly-thoi-gian","nameVi":"Quản lý thời gian","nameEn":"Time Management","category":"KY_NANG_MEM","aliases":["Time Management","Quản lý công việc","Prioritization"]},
  {"slug":"thuyet-trinh","nameVi":"Thuyết trình","nameEn":"Presentation","category":"KY_NANG_MEM","aliases":["Presentation Skills","Public Speaking","Kỹ năng thuyết trình"]},
  {"slug":"dam-phan","nameVi":"Đàm phán","nameEn":"Negotiation","category":"KY_NANG_MEM","aliases":["Negotiation","Kỹ năng đàm phán","Business Negotiation"]},
  {"slug":"tu-duy-sang-tao","nameVi":"Tư duy sáng tạo","nameEn":"Creative Thinking","category":"KY_NANG_MEM","aliases":["Creative Thinking","Creativity","Innovation","Tư duy đổi mới"]},
  {"slug":"tu-duy-phan-bien","nameVi":"Tư duy phản biện","nameEn":"Critical Thinking","category":"KY_NANG_MEM","aliases":["Critical Thinking","Analytical Thinking","Tư duy phân tích"]},
  {"slug":"lam-viec-ap-luc","nameVi":"Làm việc dưới áp lực","nameEn":"Working Under Pressure","category":"KY_NANG_MEM","aliases":["Work Under Pressure","Chịu áp lực tốt","Stress Management"]},
  {"slug":"tu-hoc-tu-phat-trien","nameVi":"Tự học & Tự phát triển","nameEn":"Self-Learning","category":"KY_NANG_MEM","aliases":["Self-Learning","Self-Development","Tự học","Lifelong Learning"]},
  {"slug":"quan-ly-cong-viec","nameVi":"Quản lý công việc & Ưu tiên","nameEn":"Task & Priority Management","category":"KY_NANG_MEM","aliases":["Task Management","Priority Management","OKRs","KPIs"]},

  {"slug":"fb-service","nameVi":"Dịch vụ F&B","nameEn":"Food & Beverage Service","category":"KHAC","aliases":["F&B","Food and Beverage","Restaurant Service","Phục vụ nhà hàng"]},
  {"slug":"bartending","nameVi":"Pha chế đồ uống","nameEn":"Bartending","category":"KHAC","aliases":["Bartender","Barista","Pha chế","Bartending"]},
  {"slug":"du-lich-khach-san","nameVi":"Du lịch & Khách sạn","nameEn":"Tourism & Hospitality","category":"KHAC","aliases":["Tourism","Hospitality","Hotel Management","Du lịch"]},
  {"slug":"phap-ly","nameVi":"Pháp lý","nameEn":"Legal","category":"KHAC","aliases":["Legal","Pháp luật","Law","Tư vấn pháp lý","In-house Legal"]},
  {"slug":"bat-dong-san","nameVi":"Bất động sản","nameEn":"Real Estate","category":"KHAC","aliases":["Real Estate","Bất động sản","Property","Môi giới BĐS"]},
  {"slug":"bao-hiem","nameVi":"Bảo hiểm","nameEn":"Insurance","category":"KHAC","aliases":["Insurance","Bảo hiểm nhân thọ","Life Insurance","Insurance Agent"]},
  {"slug":"van-thu-hanh-chinh","nameVi":"Văn thư & Hành chính","nameEn":"Administrative & Clerical","category":"KHAC","aliases":["Administrative","Hành chính văn phòng","Office Administration","Văn phòng"]},
  {"slug":"bao-ve-an-ninh","nameVi":"Bảo vệ & An ninh","nameEn":"Security Guard","category":"KHAC","aliases":["Security","Bảo vệ","Security Guard","An ninh"]},
  {"slug":"lai-xe","nameVi":"Lái xe","nameEn":"Driving","category":"KHAC","aliases":["Driving","Lái xe","Driver","Xe tải","Giao hàng"]},
  {"slug":"nong-nghiep","nameVi":"Nông nghiệp","nameEn":"Agriculture","category":"KHAC","aliases":["Agriculture","Nông nghiệp","Farming","Agri"]},
  {"slug":"bao-chi-truyen-hinh","nameVi":"Báo chí & Truyền hình","nameEn":"Journalism & Broadcasting","category":"KHAC","aliases":["Journalism","Broadcasting","Báo chí","Phóng viên","Reporter"]},
  {"slug":"luat","nameVi":"Luật","nameEn":"Law","category":"KHAC","aliases":["Lawyer","Legal Counsel","Luật sư","Luật doanh nghiệp"]}
]
